Metadata-Version: 2.1
Name: lens-bson
Version: 0.0.3
Summary: A BSON parser for lens
Home-page: https://github.com/port-zero/lens_bson
Author: Veit Heller
License: MIT
Download-URL: https://github.com/port-zero/lens_bson/tarball/0.0.3
Platform: UNKNOWN
